odoo9_addon_stock_pack_operation_auto_fill-9.0.1.0.0-py2.7-nspkg.pth
odoo9_addon_stock_pack_operation_auto_fill-9.0.1.0.0.dist-info/DESCRIPTION.rst
odoo9_addon_stock_pack_operation_auto_fill-9.0.1.0.0.dist-info/METADATA
odoo9_addon_stock_pack_operation_auto_fill-9.0.1.0.0.dist-info/RECORD
odoo9_addon_stock_pack_operation_auto_fill-9.0.1.0.0.dist-info/WHEEL
odoo9_addon_stock_pack_operation_auto_fill-9.0.1.0.0.dist-info/metadata.json
odoo9_addon_stock_pack_operation_auto_fill-9.0.1.0.0.dist-info/namespace_packages.txt
odoo9_addon_stock_pack_operation_auto_fill-9.0.1.0.0.dist-info/top_level.txt
odoo_addons/stock_pack_operation_auto_fill/README.rst
odoo_addons/stock_pack_operation_auto_fill/__init__.py
odoo_addons/stock_pack_operation_auto_fill/__openerp__.py
odoo_addons/stock_pack_operation_auto_fill/models/__init__.py
odoo_addons/stock_pack_operation_auto_fill/models/stock_picking.py
odoo_addons/stock_pack_operation_auto_fill/static/description/icon.png
odoo_addons/stock_pack_operation_auto_fill/tests/__init__.py
odoo_addons/stock_pack_operation_auto_fill/tests/test_stock_picking.py
odoo_addons/stock_pack_operation_auto_fill/views/stock_picking.xml
